{
  "schemaVersion": 1,
  "id": "simplynoreport",
  "version": "${version}",

  "name": "Simply No Report",
  "description": "Give server admins the power to disable chat reports",
  "authors": [
    "Matteo Bertucci <matteo@akarys.me>"
  ],
  "contact": {
    "sources": "https://git.akarys.me/simply-no-report"
  },

  "license": "MIT",
  "icon": "assets/simplynoreport/icon.png",

  "environment": "*",
  "entrypoints": {
    "main": [
      "me.akarys.simplynoreport.SimplyNoReport"
    ]
  },
  "mixins": [
    "simplynoreport.mixins.json"
  ],

  "depends": {
    "fabricloader": ">=0.14.6",
    "fabric": "*",
    "minecraft": "~1.19",
    "java": ">=17"
  }
}
